domaingen/__init__.py
domaingen/domains.py
domaingen-0.0.10.dist-info/LICENSE
domaingen-0.0.10.dist-info/METADATA
domaingen-0.0.10.dist-info/WHEEL
domaingen-0.0.10.dist-info/top_level.txt
domaingen-0.0.10.dist-info/RECORD
