Metadata-Version: 2.1
Name: domaingen
Version: 0.0.10
Summary: Generate domain name variations based on keywords and synonyms.
Author: GoInfosystems.com
Author-email: <info@goinfosystems.com>
Keywords: python,whois,domain,domain name,domain name registration,domain names,domains,dns
Classifier: Development Status :: 1 - Planning
Classifier: Intended Audience :: Developers
Classifier: Programming Language :: Python :: 3
Classifier: Operating System :: Unix
Classifier: Operating System :: MacOS :: MacOS X
Classifier: Operating System :: Microsoft :: Windows
License-File: LICENSE
Requires-Dist: python-whois
Requires-Dist: py-thesaurus
Requires-Dist: random-proxies
